<?xml version="1.0" encoding="UTF-8"?>
<spirit:component xmlns:xilinx="http://www.xilinx.com" xmlns:spirit="http://www.spiritconsortium.org/XMLSchema/SPIRIT/1685-2009" xmlns:xsi="http://www.w3.org/2001/XMLSchema-instance">
  <spirit:vendor>xilinx.com</spirit:vendor>
  <spirit:library>module_ref</spirit:library>
  <spirit:name>Version</spirit:name>
  <spirit:version>1.0</spirit:version>
  <spirit:busInterfaces>
    <spirit:busInterface>
      <spirit:name>s_axi</spirit:name>
      <spirit:busType spirit:vendor="xilinx.com" spirit:library="interface" spirit:name="aximm" spirit:version="1.0"/>
      <spirit:abstractionType spirit:vendor="xilinx.com" spirit:library="interface" spirit:name="aximm_rtl" spirit:version="1.0"/>
      <spirit:slave>
        <spirit:memoryMapRef spirit:memoryMapRef="s_axi"/>
      </spirit:slave>
      <spirit:portMaps>
        <spirit:portMap>
          <spirit:logicalPort>
            <spirit:name>AWADDR</spirit:name>
          </spirit:logicalPort>
          <spirit:physicalPort>
            <spirit:name>s_axi_awaddr</spirit:name>
          </spirit:physicalPort>
        </spirit:portMap>
        <spirit:portMap>
          <spirit:logicalPort>
            <spirit:name>AWPROT</spirit:name>
          </spirit:logicalPort>
          <spirit:physicalPort>
            <spirit:name>s_axi_awprot</spirit:name>
          </spirit:physicalPort>
        </spirit:portMap>
        <spirit:portMap>
          <spirit:logicalPort>
            <spirit:name>AWVALID</spirit:name>
          </spirit:logicalPort>
          <spirit:physicalPort>
            <spirit:name>s_axi_awvalid</spirit:name>
          </spirit:physicalPort>
        </spirit:portMap>
        <spirit:portMap>
          <spirit:logicalPort>
            <spirit:name>AWREADY</spirit:name>
          </spirit:logicalPort>
          <spirit:physicalPort>
            <spirit:name>s_axi_awready</spirit:name>
          </spirit:physicalPort>
        </spirit:portMap>
        <spirit:portMap>
          <spirit:logicalPort>
            <spirit:name>WDATA</spirit:name>
          </spirit:logicalPort>
          <spirit:physicalPort>
            <spirit:name>s_axi_wdata</spirit:name>
          </spirit:physicalPort>
        </spirit:portMap>
        <spirit:portMap>
          <spirit:logicalPort>
            <spirit:name>WSTRB</spirit:name>
          </spirit:logicalPort>
          <spirit:physicalPort>
            <spirit:name>s_axi_wstrb</spirit:name>
          </spirit:physicalPort>
        </spirit:portMap>
        <spirit:portMap>
          <spirit:logicalPort>
            <spirit:name>WVALID</spirit:name>
          </spirit:logicalPort>
          <spirit:physicalPort>
            <spirit:name>s_axi_wvalid</spirit:name>
          </spirit:physicalPort>
        </spirit:portMap>
        <spirit:portMap>
          <spirit:logicalPort>
            <spirit:name>WREADY</spirit:name>
          </spirit:logicalPort>
          <spirit:physicalPort>
            <spirit:name>s_axi_wready</spirit:name>
          </spirit:physicalPort>
        </spirit:portMap>
        <spirit:portMap>
          <spirit:logicalPort>
            <spirit:name>BRESP</spirit:name>
          </spirit:logicalPort>
          <spirit:physicalPort>
            <spirit:name>s_axi_bresp</spirit:name>
          </spirit:physicalPort>
        </spirit:portMap>
        <spirit:portMap>
          <spirit:logicalPort>
            <spirit:name>BVALID</spirit:name>
          </spirit:logicalPort>
          <spirit:physicalPort>
            <spirit:name>s_axi_bvalid</spirit:name>
          </spirit:physicalPort>
        </spirit:portMap>
        <spirit:portMap>
          <spirit:logicalPort>
            <spirit:name>BREADY</spirit:name>
          </spirit:logicalPort>
          <spirit:physicalPort>
            <spirit:name>s_axi_bready</spirit:name>
          </spirit:physicalPort>
        </spirit:portMap>
        <spirit:portMap>
          <spirit:logicalPort>
            <spirit:name>ARADDR</spirit:name>
          </spirit:logicalPort>
          <spirit:physicalPort>
            <spirit:name>s_axi_araddr</spirit:name>
          </spirit:physicalPort>
        </spirit:portMap>
        <spirit:portMap>
          <spirit:logicalPort>
            <spirit:name>ARPROT</spirit:name>
          </spirit:logicalPort>
          <spirit:physicalPort>
            <spirit:name>s_axi_arprot</spirit:name>
          </spirit:physicalPort>
        </spirit:portMap>
        <spirit:portMap>
          <spirit:logicalPort>
            <spirit:name>ARVALID</spirit:name>
          </spirit:logicalPort>
          <spirit:physicalPort>
            <spirit:name>s_axi_arvalid</spirit:name>
          </spirit:physicalPort>
        </spirit:portMap>
        <spirit:portMap>
          <spirit:logicalPort>
            <spirit:name>ARREADY</spirit:name>
          </spirit:logicalPort>
          <spirit:physicalPort>
            <spirit:name>s_axi_arready</spirit:name>
          </spirit:physicalPort>
        </spirit:portMap>
        <spirit:portMap>
          <spirit:logicalPort>
            <spirit:name>RDATA</spirit:name>
          </spirit:logicalPort>
          <spirit:physicalPort>
            <spirit:name>s_axi_rdata</spirit:name>
          </spirit:physicalPort>
        </spirit:portMap>
        <spirit:portMap>
          <spirit:logicalPort>
            <spirit:name>RRESP</spirit:name>
          </spirit:logicalPort>
          <spirit:physicalPort>
            <spirit:name>s_axi_rresp</spirit:name>
          </spirit:physicalPort>
        </spirit:portMap>
        <spirit:portMap>
          <spirit:logicalPort>
            <spirit:name>RVALID</spirit:name>
          </spirit:logicalPort>
          <spirit:physicalPort>
            <spirit:name>s_axi_rvalid</spirit:name>
          </spirit:physicalPort>
        </spirit:portMap>
        <spirit:portMap>
          <spirit:logicalPort>
            <spirit:name>RREADY</spirit:name>
          </spirit:logicalPort>
          <spirit:physicalPort>
            <spirit:name>s_axi_rready</spirit:name>
          </spirit:physicalPort>
        </spirit:portMap>
      </spirit:portMaps>
    </spirit:busInterface>
    <spirit:busInterface>
      <spirit:name>s_axi_aresetn</spirit:name>
      <spirit:busType spirit:vendor="xilinx.com" spirit:library="signal" spirit:name="reset" spirit:version="1.0"/>
      <spirit:abstractionType spirit:vendor="xilinx.com" spirit:library="signal" spirit:name="reset_rtl" spirit:version="1.0"/>
      <spirit:slave/>
      <spirit:portMaps>
        <spirit:portMap>
          <spirit:logicalPort>
            <spirit:name>RST</spirit:name>
          </spirit:logicalPort>
          <spirit:physicalPort>
            <spirit:name>s_axi_aresetn</spirit:name>
          </spirit:physicalPort>
        </spirit:portMap>
      </spirit:portMaps>
      <spirit:parameters>
        <spirit:parameter>
          <spirit:name>POLARITY</spirit:name>
          <spirit:value spirit:id="BUSIFPARAM_VALUE.S_AXI_ARESETN.POLARITY" spirit:choiceRef="choice_list_74b5137e">ACTIVE_LOW</spirit:value>
        </spirit:parameter>
      </spirit:parameters>
    </spirit:busInterface>
    <spirit:busInterface>
      <spirit:name>s_axi_aclk</spirit:name>
      <spirit:busType spirit:vendor="xilinx.com" spirit:library="signal" spirit:name="clock" spirit:version="1.0"/>
      <spirit:abstractionType spirit:vendor="xilinx.com" spirit:library="signal" spirit:name="clock_rtl" spirit:version="1.0"/>
      <spirit:slave/>
      <spirit:portMaps>
        <spirit:portMap>
          <spirit:logicalPort>
            <spirit:name>CLK</spirit:name>
          </spirit:logicalPort>
          <spirit:physicalPort>
            <spirit:name>s_axi_aclk</spirit:name>
          </spirit:physicalPort>
        </spirit:portMap>
      </spirit:portMaps>
      <spirit:parameters>
        <spirit:parameter>
          <spirit:name>ASSOCIATED_BUSIF</spirit:name>
          <spirit:value spirit:id="BUSIFPARAM_VALUE.S_AXI_ACLK.ASSOCIATED_BUSIF">s_axi</spirit:value>
        </spirit:parameter>
        <spirit:parameter>
          <spirit:name>ASSOCIATED_RESET</spirit:name>
          <spirit:value spirit:id="BUSIFPARAM_VALUE.S_AXI_ACLK.ASSOCIATED_RESET">s_axi_aresetn</spirit:value>
        </spirit:parameter>
      </spirit:parameters>
    </spirit:busInterface>
  </spirit:busInterfaces>
  <spirit:memoryMaps>
    <spirit:memoryMap>
      <spirit:name>s_axi</spirit:name>
      <spirit:displayName>s_axi</spirit:displayName>
      <spirit:addressBlock>
        <spirit:name>reg0</spirit:name>
        <spirit:displayName>reg0</spirit:displayName>
        <spirit:baseAddress spirit:format="bitString" spirit:bitStringLength="1">0x0</spirit:baseAddress>
        <spirit:range spirit:format="long" spirit:resolve="dependent" spirit:dependency="pow(2,(spirit:decode(id(&apos;MODELPARAM_VALUE.C_S00_AXI_ADDR_WIDTH&apos;)) - 1) - 0 + 1)" spirit:minimum="4096" spirit:rangeType="long">4096</spirit:range>
        <spirit:width spirit:format="long" spirit:resolve="dependent" spirit:dependency="(spirit:decode(id(&apos;MODELPARAM_VALUE.C_S00_AXI_DATA_WIDTH&apos;)) - 1) - 0 + 1">32</spirit:width>
        <spirit:usage>register</spirit:usage>
      </spirit:addressBlock>
    </spirit:memoryMap>
  </spirit:memoryMaps>
  <spirit:model>
    <spirit:views>
      <spirit:view>
        <spirit:name>xilinx_anylanguagesynthesis</spirit:name>
        <spirit:displayName>Synthesis</spirit:displayName>
        <spirit:envIdentifier>:vivado.xilinx.com:synthesis</spirit:envIdentifier>
        <spirit:language>Verilog</spirit:language>
        <spirit:modelName>Version</spirit:modelName>
        <spirit:parameters>
          <spirit:parameter>
            <spirit:name>viewChecksum</spirit:name>
            <spirit:value>f5264ccc</spirit:value>
          </spirit:parameter>
        </spirit:parameters>
      </spirit:view>
      <spirit:view>
        <spirit:name>xilinx_anylanguagebehavioralsimulation</spirit:name>
        <spirit:displayName>Simulation</spirit:displayName>
        <spirit:envIdentifier>:vivado.xilinx.com:simulation</spirit:envIdentifier>
        <spirit:language>Verilog</spirit:language>
        <spirit:modelName>Version</spirit:modelName>
        <spirit:parameters>
          <spirit:parameter>
            <spirit:name>viewChecksum</spirit:name>
            <spirit:value>f5264ccc</spirit:value>
          </spirit:parameter>
        </spirit:parameters>
      </spirit:view>
      <spirit:view>
        <spirit:name>xilinx_xpgui</spirit:name>
        <spirit:displayName>UI Layout</spirit:displayName>
        <spirit:envIdentifier>:vivado.xilinx.com:xgui.ui</spirit:envIdentifier>
        <spirit:fileSetRef>
          <spirit:localName>xilinx_xpgui_view_fileset</spirit:localName>
        </spirit:fileSetRef>
      </spirit:view>
    </spirit:views>
    <spirit:ports>
      <spirit:port>
        <spirit:name>s_axi_aclk</spirit:name>
        <spirit:wire>
          <spirit:direction>in</spirit:direction>
          <spirit:wireTypeDefs>
            <spirit:wireTypeDef>
              <spirit:typeName>wire</spirit:typeName>
              <spirit:viewNameRef>xilinx_anylanguagesynthesis</spirit:viewNameRef>
              <spirit:viewNameRef>xilinx_anylanguagebehavioralsimulation</spirit:viewNameRef>
            </spirit:wireTypeDef>
          </spirit:wireTypeDefs>
        </spirit:wire>
      </spirit:port>
      <spirit:port>
        <spirit:name>s_axi_aresetn</spirit:name>
        <spirit:wire>
          <spirit:direction>in</spirit:direction>
          <spirit:wireTypeDefs>
            <spirit:wireTypeDef>
              <spirit:typeName>wire</spirit:typeName>
              <spirit:viewNameRef>xilinx_anylanguagesynthesis</spirit:viewNameRef>
              <spirit:viewNameRef>xilinx_anylanguagebehavioralsimulation</spirit:viewNameRef>
            </spirit:wireTypeDef>
          </spirit:wireTypeDefs>
        </spirit:wire>
      </spirit:port>
      <spirit:port>
        <spirit:name>s_axi_awaddr</spirit:name>
        <spirit:wire>
          <spirit:direction>in</spirit:direction>
          <spirit:vector>
            <spirit:left spirit:format="long" spirit:resolve="dependent" spirit:dependency="(spirit:decode(id(&apos;MODELPARAM_VALUE.C_S00_AXI_ADDR_WIDTH&apos;)) - 1)">6</spirit:left>
            <spirit:right spirit:format="long">0</spirit:right>
          </spirit:vector>
          <spirit:wireTypeDefs>
            <spirit:wireTypeDef>
              <spirit:typeName>wire</spirit:typeName>
              <spirit:viewNameRef>xilinx_anylanguagesynthesis</spirit:viewNameRef>
              <spirit:viewNameRef>xilinx_anylanguagebehavioralsimulation</spirit:viewNameRef>
            </spirit:wireTypeDef>
          </spirit:wireTypeDefs>
          <spirit:driver>
            <spirit:defaultValue spirit:format="long">0</spirit:defaultValue>
          </spirit:driver>
        </spirit:wire>
      </spirit:port>
      <spirit:port>
        <spirit:name>s_axi_awprot</spirit:name>
        <spirit:wire>
          <spirit:direction>in</spirit:direction>
          <spirit:vector>
            <spirit:left spirit:format="long">2</spirit:left>
            <spirit:right spirit:format="long">0</spirit:right>
          </spirit:vector>
          <spirit:wireTypeDefs>
            <spirit:wireTypeDef>
              <spirit:typeName>wire</spirit:typeName>
              <spirit:viewNameRef>xilinx_anylanguagesynthesis</spirit:viewNameRef>
              <spirit:viewNameRef>xilinx_anylanguagebehavioralsimulation</spirit:viewNameRef>
            </spirit:wireTypeDef>
          </spirit:wireTypeDefs>
          <spirit:driver>
            <spirit:defaultValue spirit:format="long">0</spirit:defaultValue>
          </spirit:driver>
        </spirit:wire>
      </spirit:port>
      <spirit:port>
        <spirit:name>s_axi_awvalid</spirit:name>
        <spirit:wire>
          <spirit:direction>in</spirit:direction>
          <spirit:wireTypeDefs>
            <spirit:wireTypeDef>
              <spirit:typeName>wire</spirit:typeName>
              <spirit:viewNameRef>xilinx_anylanguagesynthesis</spirit:viewNameRef>
              <spirit:viewNameRef>xilinx_anylanguagebehavioralsimulation</spirit:viewNameRef>
            </spirit:wireTypeDef>
          </spirit:wireTypeDefs>
          <spirit:driver>
            <spirit:defaultValue spirit:format="long">0</spirit:defaultValue>
          </spirit:driver>
        </spirit:wire>
      </spirit:port>
      <spirit:port>
        <spirit:name>s_axi_awready</spirit:name>
        <spirit:wire>
          <spirit:direction>out</spirit:direction>
          <spirit:wireTypeDefs>
            <spirit:wireTypeDef>
              <spirit:typeName>wire</spirit:typeName>
              <spirit:viewNameRef>xilinx_anylanguagesynthesis</spirit:viewNameRef>
              <spirit:viewNameRef>xilinx_anylanguagebehavioralsimulation</spirit:viewNameRef>
            </spirit:wireTypeDef>
          </spirit:wireTypeDefs>
        </spirit:wire>
      </spirit:port>
      <spirit:port>
        <spirit:name>s_axi_wdata</spirit:name>
        <spirit:wire>
          <spirit:direction>in</spirit:direction>
          <spirit:vector>
            <spirit:left spirit:format="long" spirit:resolve="dependent" spirit:dependency="(spirit:decode(id(&apos;MODELPARAM_VALUE.C_S00_AXI_DATA_WIDTH&apos;)) - 1)">31</spirit:left>
            <spirit:right spirit:format="long">0</spirit:right>
          </spirit:vector>
          <spirit:wireTypeDefs>
            <spirit:wireTypeDef>
              <spirit:typeName>wire</spirit:typeName>
              <spirit:viewNameRef>xilinx_anylanguagesynthesis</spirit:viewNameRef>
              <spirit:viewNameRef>xilinx_anylanguagebehavioralsimulation</spirit:viewNameRef>
            </spirit:wireTypeDef>
          </spirit:wireTypeDefs>
          <spirit:driver>
            <spirit:defaultValue spirit:format="long">0</spirit:defaultValue>
          </spirit:driver>
        </spirit:wire>
      </spirit:port>
      <spirit:port>
        <spirit:name>s_axi_wstrb</spirit:name>
        <spirit:wire>
          <spirit:direction>in</spirit:direction>
          <spirit:vector>
            <spirit:left spirit:format="long" spirit:resolve="dependent" spirit:dependency="((spirit:decode(id(&apos;MODELPARAM_VALUE.C_S00_AXI_DATA_WIDTH&apos;)) / 8) - 1)">3</spirit:left>
            <spirit:right spirit:format="long">0</spirit:right>
          </spirit:vector>
          <spirit:wireTypeDefs>
            <spirit:wireTypeDef>
              <spirit:typeName>wire</spirit:typeName>
              <spirit:viewNameRef>xilinx_anylanguagesynthesis</spirit:viewNameRef>
              <spirit:viewNameRef>xilinx_anylanguagebehavioralsimulation</spirit:viewNameRef>
            </spirit:wireTypeDef>
          </spirit:wireTypeDefs>
          <spirit:driver>
            <spirit:defaultValue spirit:format="long">1</spirit:defaultValue>
          </spirit:driver>
        </spirit:wire>
      </spirit:port>
      <spirit:port>
        <spirit:name>s_axi_wvalid</spirit:name>
        <spirit:wire>
          <spirit:direction>in</spirit:direction>
          <spirit:wireTypeDefs>
            <spirit:wireTypeDef>
              <spirit:typeName>wire</spirit:typeName>
              <spirit:viewNameRef>xilinx_anylanguagesynthesis</spirit:viewNameRef>
              <spirit:viewNameRef>xilinx_anylanguagebehavioralsimulation</spirit:viewNameRef>
            </spirit:wireTypeDef>
          </spirit:wireTypeDefs>
          <spirit:driver>
            <spirit:defaultValue spirit:format="long">0</spirit:defaultValue>
          </spirit:driver>
        </spirit:wire>
      </spirit:port>
      <spirit:port>
        <spirit:name>s_axi_wready</spirit:name>
        <spirit:wire>
          <spirit:direction>out</spirit:direction>
          <spirit:wireTypeDefs>
            <spirit:wireTypeDef>
              <spirit:typeName>wire</spirit:typeName>
              <spirit:viewNameRef>xilinx_anylanguagesynthesis</spirit:viewNameRef>
              <spirit:viewNameRef>xilinx_anylanguagebehavioralsimulation</spirit:viewNameRef>
            </spirit:wireTypeDef>
          </spirit:wireTypeDefs>
        </spirit:wire>
      </spirit:port>
      <spirit:port>
        <spirit:name>s_axi_bresp</spirit:name>
        <spirit:wire>
          <spirit:direction>out</spirit:direction>
          <spirit:vector>
            <spirit:left spirit:format="long">1</spirit:left>
            <spirit:right spirit:format="long">0</spirit:right>
          </spirit:vector>
          <spirit:wireTypeDefs>
            <spirit:wireTypeDef>
              <spirit:typeName>wire</spirit:typeName>
              <spirit:viewNameRef>xilinx_anylanguagesynthesis</spirit:viewNameRef>
              <spirit:viewNameRef>xilinx_anylanguagebehavioralsimulation</spirit:viewNameRef>
            </spirit:wireTypeDef>
          </spirit:wireTypeDefs>
        </spirit:wire>
      </spirit:port>
      <spirit:port>
        <spirit:name>s_axi_bvalid</spirit:name>
        <spirit:wire>
          <spirit:direction>out</spirit:direction>
          <spirit:wireTypeDefs>
            <spirit:wireTypeDef>
              <spirit:typeName>wire</spirit:typeName>
              <spirit:viewNameRef>xilinx_anylanguagesynthesis</spirit:viewNameRef>
              <spirit:viewNameRef>xilinx_anylanguagebehavioralsimulation</spirit:viewNameRef>
            </spirit:wireTypeDef>
          </spirit:wireTypeDefs>
        </spirit:wire>
      </spirit:port>
      <spirit:port>
        <spirit:name>s_axi_bready</spirit:name>
        <spirit:wire>
          <spirit:direction>in</spirit:direction>
          <spirit:wireTypeDefs>
            <spirit:wireTypeDef>
              <spirit:typeName>wire</spirit:typeName>
              <spirit:viewNameRef>xilinx_anylanguagesynthesis</spirit:viewNameRef>
              <spirit:viewNameRef>xilinx_anylanguagebehavioralsimulation</spirit:viewNameRef>
            </spirit:wireTypeDef>
          </spirit:wireTypeDefs>
          <spirit:driver>
            <spirit:defaultValue spirit:format="long">0</spirit:defaultValue>
          </spirit:driver>
        </spirit:wire>
      </spirit:port>
      <spirit:port>
        <spirit:name>s_axi_araddr</spirit:name>
        <spirit:wire>
          <spirit:direction>in</spirit:direction>
          <spirit:vector>
            <spirit:left spirit:format="long" spirit:resolve="dependent" spirit:dependency="(spirit:decode(id(&apos;MODELPARAM_VALUE.C_S00_AXI_ADDR_WIDTH&apos;)) - 1)">6</spirit:left>
            <spirit:right spirit:format="long">0</spirit:right>
          </spirit:vector>
          <spirit:wireTypeDefs>
            <spirit:wireTypeDef>
              <spirit:typeName>wire</spirit:typeName>
              <spirit:viewNameRef>xilinx_anylanguagesynthesis</spirit:viewNameRef>
              <spirit:viewNameRef>xilinx_anylanguagebehavioralsimulation</spirit:viewNameRef>
            </spirit:wireTypeDef>
          </spirit:wireTypeDefs>
          <spirit:driver>
            <spirit:defaultValue spirit:format="long">0</spirit:defaultValue>
          </spirit:driver>
        </spirit:wire>
      </spirit:port>
      <spirit:port>
        <spirit:name>s_axi_arprot</spirit:name>
        <spirit:wire>
          <spirit:direction>in</spirit:direction>
          <spirit:vector>
            <spirit:left spirit:format="long">2</spirit:left>
            <spirit:right spirit:format="long">0</spirit:right>
          </spirit:vector>
          <spirit:wireTypeDefs>
            <spirit:wireTypeDef>
              <spirit:typeName>wire</spirit:typeName>
              <spirit:viewNameRef>xilinx_anylanguagesynthesis</spirit:viewNameRef>
              <spirit:viewNameRef>xilinx_anylanguagebehavioralsimulation</spirit:viewNameRef>
            </spirit:wireTypeDef>
          </spirit:wireTypeDefs>
          <spirit:driver>
            <spirit:defaultValue spirit:format="long">0</spirit:defaultValue>
          </spirit:driver>
        </spirit:wire>
      </spirit:port>
      <spirit:port>
        <spirit:name>s_axi_arvalid</spirit:name>
        <spirit:wire>
          <spirit:direction>in</spirit:direction>
          <spirit:wireTypeDefs>
            <spirit:wireTypeDef>
              <spirit:typeName>wire</spirit:typeName>
              <spirit:viewNameRef>xilinx_anylanguagesynthesis</spirit:viewNameRef>
              <spirit:viewNameRef>xilinx_anylanguagebehavioralsimulation</spirit:viewNameRef>
            </spirit:wireTypeDef>
          </spirit:wireTypeDefs>
          <spirit:driver>
            <spirit:defaultValue spirit:format="long">0</spirit:defaultValue>
          </spirit:driver>
        </spirit:wire>
      </spirit:port>
      <spirit:port>
        <spirit:name>s_axi_arready</spirit:name>
        <spirit:wire>
          <spirit:direction>out</spirit:direction>
          <spirit:wireTypeDefs>
            <spirit:wireTypeDef>
              <spirit:typeName>wire</spirit:typeName>
              <spirit:viewNameRef>xilinx_anylanguagesynthesis</spirit:viewNameRef>
              <spirit:viewNameRef>xilinx_anylanguagebehavioralsimulation</spirit:viewNameRef>
            </spirit:wireTypeDef>
          </spirit:wireTypeDefs>
        </spirit:wire>
      </spirit:port>
      <spirit:port>
        <spirit:name>s_axi_rdata</spirit:name>
        <spirit:wire>
          <spirit:direction>out</spirit:direction>
          <spirit:vector>
            <spirit:left spirit:format="long" spirit:resolve="dependent" spirit:dependency="(spirit:decode(id(&apos;MODELPARAM_VALUE.C_S00_AXI_DATA_WIDTH&apos;)) - 1)">31</spirit:left>
            <spirit:right spirit:format="long">0</spirit:right>
          </spirit:vector>
          <spirit:wireTypeDefs>
            <spirit:wireTypeDef>
              <spirit:typeName>wire</spirit:typeName>
              <spirit:viewNameRef>xilinx_anylanguagesynthesis</spirit:viewNameRef>
              <spirit:viewNameRef>xilinx_anylanguagebehavioralsimulation</spirit:viewNameRef>
            </spirit:wireTypeDef>
          </spirit:wireTypeDefs>
        </spirit:wire>
      </spirit:port>
      <spirit:port>
        <spirit:name>s_axi_rresp</spirit:name>
        <spirit:wire>
          <spirit:direction>out</spirit:direction>
          <spirit:vector>
            <spirit:left spirit:format="long">1</spirit:left>
            <spirit:right spirit:format="long">0</spirit:right>
          </spirit:vector>
          <spirit:wireTypeDefs>
            <spirit:wireTypeDef>
              <spirit:typeName>wire</spirit:typeName>
              <spirit:viewNameRef>xilinx_anylanguagesynthesis</spirit:viewNameRef>
              <spirit:viewNameRef>xilinx_anylanguagebehavioralsimulation</spirit:viewNameRef>
            </spirit:wireTypeDef>
          </spirit:wireTypeDefs>
        </spirit:wire>
      </spirit:port>
      <spirit:port>
        <spirit:name>s_axi_rvalid</spirit:name>
        <spirit:wire>
          <spirit:direction>out</spirit:direction>
          <spirit:wireTypeDefs>
            <spirit:wireTypeDef>
              <spirit:typeName>wire</spirit:typeName>
              <spirit:viewNameRef>xilinx_anylanguagesynthesis</spirit:viewNameRef>
              <spirit:viewNameRef>xilinx_anylanguagebehavioralsimulation</spirit:viewNameRef>
            </spirit:wireTypeDef>
          </spirit:wireTypeDefs>
        </spirit:wire>
      </spirit:port>
      <spirit:port>
        <spirit:name>s_axi_rready</spirit:name>
        <spirit:wire>
          <spirit:direction>in</spirit:direction>
          <spirit:wireTypeDefs>
            <spirit:wireTypeDef>
              <spirit:typeName>wire</spirit:typeName>
              <spirit:viewNameRef>xilinx_anylanguagesynthesis</spirit:viewNameRef>
              <spirit:viewNameRef>xilinx_anylanguagebehavioralsimulation</spirit:viewNameRef>
            </spirit:wireTypeDef>
          </spirit:wireTypeDefs>
          <spirit:driver>
            <spirit:defaultValue spirit:format="long">0</spirit:defaultValue>
          </spirit:driver>
        </spirit:wire>
      </spirit:port>
    </spirit:ports>
    <spirit:modelParameters>
      <spirit:modelParameter xsi:type="spirit:nameValueTypeType" spirit:dataType="integer">
        <spirit:name>VERSION_YYYY</spirit:name>
        <spirit:displayName>Version Yyyy</spirit:displayName>
        <spirit:value spirit:format="long" spirit:resolve="generated" spirit:id="MODELPARAM_VALUE.VERSION_YYYY">2025</spirit:value>
      </spirit:modelParameter>
      <spirit:modelParameter spirit:dataType="integer">
        <spirit:name>VERSION_MM</spirit:name>
        <spirit:displayName>Version Mm</spirit:displayName>
        <spirit:value spirit:format="long" spirit:resolve="generated" spirit:id="MODELPARAM_VALUE.VERSION_MM">8</spirit:value>
      </spirit:modelParameter>
      <spirit:modelParameter spirit:dataType="integer">
        <spirit:name>VERSION_DD</spirit:name>
        <spirit:displayName>Version Dd</spirit:displayName>
        <spirit:value spirit:format="long" spirit:resolve="generated" spirit:id="MODELPARAM_VALUE.VERSION_DD">14</spirit:value>
      </spirit:modelParameter>
      <spirit:modelParameter spirit:dataType="integer">
        <spirit:name>VERSION_MAJ</spirit:name>
        <spirit:displayName>Version Maj</spirit:displayName>
        <spirit:value spirit:format="long" spirit:resolve="generated" spirit:id="MODELPARAM_VALUE.VERSION_MAJ">0</spirit:value>
      </spirit:modelParameter>
      <spirit:modelParameter spirit:dataType="integer">
        <spirit:name>VERSION_MIN</spirit:name>
        <spirit:displayName>Version Min</spirit:displayName>
        <spirit:value spirit:format="long" spirit:resolve="generated" spirit:id="MODELPARAM_VALUE.VERSION_MIN">2</spirit:value>
      </spirit:modelParameter>
      <spirit:modelParameter spirit:dataType="integer">
        <spirit:name>VERSION_REV</spirit:name>
        <spirit:displayName>Version Rev</spirit:displayName>
        <spirit:value spirit:format="long" spirit:resolve="generated" spirit:id="MODELPARAM_VALUE.VERSION_REV">1</spirit:value>
      </spirit:modelParameter>
      <spirit:modelParameter spirit:dataType="integer">
        <spirit:name>VERSION_COMPANY</spirit:name>
        <spirit:displayName>Version Company</spirit:displayName>
        <spirit:value spirit:format="long" spirit:resolve="generated" spirit:id="MODELPARAM_VALUE.VERSION_COMPANY">1</spirit:value>
      </spirit:modelParameter>
      <spirit:modelParameter spirit:dataType="integer">
        <spirit:name>VERSION_MODE</spirit:name>
        <spirit:displayName>Version Mode</spirit:displayName>
        <spirit:value spirit:format="long" spirit:resolve="generated" spirit:id="MODELPARAM_VALUE.VERSION_MODE">1</spirit:value>
      </spirit:modelParameter>
      <spirit:modelParameter spirit:dataType="integer">
        <spirit:name>VERSION_BOARD</spirit:name>
        <spirit:displayName>Version Board</spirit:displayName>
        <spirit:value spirit:format="long" spirit:resolve="generated" spirit:id="MODELPARAM_VALUE.VERSION_BOARD">1</spirit:value>
      </spirit:modelParameter>
      <spirit:modelParameter spirit:dataType="integer">
        <spirit:name>VERSION_HW</spirit:name>
        <spirit:displayName>Version Hw</spirit:displayName>
        <spirit:value spirit:format="long" spirit:resolve="generated" spirit:id="MODELPARAM_VALUE.VERSION_HW">1</spirit:value>
      </spirit:modelParameter>
      <spirit:modelParameter spirit:dataType="integer">
        <spirit:name>NOTE_LENGTH</spirit:name>
        <spirit:displayName>Note Length</spirit:displayName>
        <spirit:value spirit:format="long" spirit:resolve="generated" spirit:id="MODELPARAM_VALUE.NOTE_LENGTH">112</spirit:value>
      </spirit:modelParameter>
      <spirit:modelParameter spirit:dataType="string">
        <spirit:name>TEXT_0</spirit:name>
        <spirit:displayName>Text 0</spirit:displayName>
        <spirit:value spirit:resolve="generated" spirit:id="MODELPARAM_VALUE.TEXT_0">Viva</spirit:value>
      </spirit:modelParameter>
      <spirit:modelParameter spirit:dataType="string">
        <spirit:name>TEXT_1</spirit:name>
        <spirit:displayName>Text 1</spirit:displayName>
        <spirit:value spirit:resolve="generated" spirit:id="MODELPARAM_VALUE.TEXT_1">do 2</spirit:value>
      </spirit:modelParameter>
      <spirit:modelParameter spirit:dataType="string">
        <spirit:name>TEXT_2</spirit:name>
        <spirit:displayName>Text 2</spirit:displayName>
        <spirit:value spirit:resolve="generated" spirit:id="MODELPARAM_VALUE.TEXT_2">024.</spirit:value>
      </spirit:modelParameter>
      <spirit:modelParameter spirit:dataType="string">
        <spirit:name>TEXT_3</spirit:name>
        <spirit:displayName>Text 3</spirit:displayName>
        <spirit:value spirit:resolve="generated" spirit:id="MODELPARAM_VALUE.TEXT_3">2 - </spirit:value>
      </spirit:modelParameter>
      <spirit:modelParameter spirit:dataType="string">
        <spirit:name>TEXT_4</spirit:name>
        <spirit:displayName>Text 4</spirit:displayName>
        <spirit:value spirit:resolve="generated" spirit:id="MODELPARAM_VALUE.TEXT_4">    </spirit:value>
      </spirit:modelParameter>
      <spirit:modelParameter spirit:dataType="string">
        <spirit:name>TEXT_5</spirit:name>
        <spirit:displayName>Text 5</spirit:displayName>
        <spirit:value spirit:resolve="generated" spirit:id="MODELPARAM_VALUE.TEXT_5">    </spirit:value>
      </spirit:modelParameter>
      <spirit:modelParameter spirit:dataType="string">
        <spirit:name>TEXT_6</spirit:name>
        <spirit:displayName>Text 6</spirit:displayName>
        <spirit:value spirit:resolve="generated" spirit:id="MODELPARAM_VALUE.TEXT_6">    </spirit:value>
      </spirit:modelParameter>
      <spirit:modelParameter spirit:dataType="string">
        <spirit:name>TEXT_7</spirit:name>
        <spirit:displayName>Text 7</spirit:displayName>
        <spirit:value spirit:resolve="generated" spirit:id="MODELPARAM_VALUE.TEXT_7">    </spirit:value>
      </spirit:modelParameter>
      <spirit:modelParameter spirit:dataType="string">
        <spirit:name>TEXT_8</spirit:name>
        <spirit:displayName>Text 8</spirit:displayName>
        <spirit:value spirit:resolve="generated" spirit:id="MODELPARAM_VALUE.TEXT_8">    </spirit:value>
      </spirit:modelParameter>
      <spirit:modelParameter spirit:dataType="string">
        <spirit:name>TEXT_9</spirit:name>
        <spirit:displayName>Text 9</spirit:displayName>
        <spirit:value spirit:resolve="generated" spirit:id="MODELPARAM_VALUE.TEXT_9">    </spirit:value>
      </spirit:modelParameter>
      <spirit:modelParameter spirit:dataType="string">
        <spirit:name>TEXT_10</spirit:name>
        <spirit:displayName>Text 10</spirit:displayName>
        <spirit:value spirit:resolve="generated" spirit:id="MODELPARAM_VALUE.TEXT_10">    </spirit:value>
      </spirit:modelParameter>
      <spirit:modelParameter spirit:dataType="string">
        <spirit:name>TEXT_11</spirit:name>
        <spirit:displayName>Text 11</spirit:displayName>
        <spirit:value spirit:resolve="generated" spirit:id="MODELPARAM_VALUE.TEXT_11">    </spirit:value>
      </spirit:modelParameter>
      <spirit:modelParameter spirit:dataType="string">
        <spirit:name>TEXT_12</spirit:name>
        <spirit:displayName>Text 12</spirit:displayName>
        <spirit:value spirit:resolve="generated" spirit:id="MODELPARAM_VALUE.TEXT_12">    </spirit:value>
      </spirit:modelParameter>
      <spirit:modelParameter spirit:dataType="string">
        <spirit:name>TEXT_13</spirit:name>
        <spirit:displayName>Text 13</spirit:displayName>
        <spirit:value spirit:resolve="generated" spirit:id="MODELPARAM_VALUE.TEXT_13">    </spirit:value>
      </spirit:modelParameter>
      <spirit:modelParameter spirit:dataType="string">
        <spirit:name>TEXT_14</spirit:name>
        <spirit:displayName>Text 14</spirit:displayName>
        <spirit:value spirit:resolve="generated" spirit:id="MODELPARAM_VALUE.TEXT_14">    </spirit:value>
      </spirit:modelParameter>
      <spirit:modelParameter spirit:dataType="string">
        <spirit:name>TEXT_15</spirit:name>
        <spirit:displayName>Text 15</spirit:displayName>
        <spirit:value spirit:resolve="generated" spirit:id="MODELPARAM_VALUE.TEXT_15">    </spirit:value>
      </spirit:modelParameter>
      <spirit:modelParameter spirit:dataType="string">
        <spirit:name>TEXT_16</spirit:name>
        <spirit:displayName>Text 16</spirit:displayName>
        <spirit:value spirit:resolve="generated" spirit:id="MODELPARAM_VALUE.TEXT_16">    </spirit:value>
      </spirit:modelParameter>
      <spirit:modelParameter spirit:dataType="string">
        <spirit:name>TEXT_17</spirit:name>
        <spirit:displayName>Text 17</spirit:displayName>
        <spirit:value spirit:resolve="generated" spirit:id="MODELPARAM_VALUE.TEXT_17">    </spirit:value>
      </spirit:modelParameter>
      <spirit:modelParameter spirit:dataType="string">
        <spirit:name>TEXT_18</spirit:name>
        <spirit:displayName>Text 18</spirit:displayName>
        <spirit:value spirit:resolve="generated" spirit:id="MODELPARAM_VALUE.TEXT_18">    </spirit:value>
      </spirit:modelParameter>
      <spirit:modelParameter spirit:dataType="string">
        <spirit:name>TEXT_19</spirit:name>
        <spirit:displayName>Text 19</spirit:displayName>
        <spirit:value spirit:resolve="generated" spirit:id="MODELPARAM_VALUE.TEXT_19">    </spirit:value>
      </spirit:modelParameter>
      <spirit:modelParameter spirit:dataType="string">
        <spirit:name>TEXT_20</spirit:name>
        <spirit:displayName>Text 20</spirit:displayName>
        <spirit:value spirit:resolve="generated" spirit:id="MODELPARAM_VALUE.TEXT_20">    </spirit:value>
      </spirit:modelParameter>
      <spirit:modelParameter spirit:dataType="string">
        <spirit:name>TEXT_21</spirit:name>
        <spirit:displayName>Text 21</spirit:displayName>
        <spirit:value spirit:resolve="generated" spirit:id="MODELPARAM_VALUE.TEXT_21">    </spirit:value>
      </spirit:modelParameter>
      <spirit:modelParameter spirit:dataType="string">
        <spirit:name>TEXT_22</spirit:name>
        <spirit:displayName>Text 22</spirit:displayName>
        <spirit:value spirit:resolve="generated" spirit:id="MODELPARAM_VALUE.TEXT_22">    </spirit:value>
      </spirit:modelParameter>
      <spirit:modelParameter spirit:dataType="string">
        <spirit:name>TEXT_23</spirit:name>
        <spirit:displayName>Text 23</spirit:displayName>
        <spirit:value spirit:resolve="generated" spirit:id="MODELPARAM_VALUE.TEXT_23">    </spirit:value>
      </spirit:modelParameter>
      <spirit:modelParameter spirit:dataType="string">
        <spirit:name>TEXT_24</spirit:name>
        <spirit:displayName>Text 24</spirit:displayName>
        <spirit:value spirit:resolve="generated" spirit:id="MODELPARAM_VALUE.TEXT_24">    </spirit:value>
      </spirit:modelParameter>
      <spirit:modelParameter spirit:dataType="string">
        <spirit:name>TEXT_25</spirit:name>
        <spirit:displayName>Text 25</spirit:displayName>
        <spirit:value spirit:resolve="generated" spirit:id="MODELPARAM_VALUE.TEXT_25">    </spirit:value>
      </spirit:modelParameter>
      <spirit:modelParameter spirit:dataType="string">
        <spirit:name>TEXT_26</spirit:name>
        <spirit:displayName>Text 26</spirit:displayName>
        <spirit:value spirit:resolve="generated" spirit:id="MODELPARAM_VALUE.TEXT_26">    </spirit:value>
      </spirit:modelParameter>
      <spirit:modelParameter spirit:dataType="string">
        <spirit:name>TEXT_27</spirit:name>
        <spirit:displayName>Text 27</spirit:displayName>
        <spirit:value spirit:resolve="generated" spirit:id="MODELPARAM_VALUE.TEXT_27">    </spirit:value>
      </spirit:modelParameter>
      <spirit:modelParameter spirit:dataType="integer">
        <spirit:name>C_S00_AXI_DATA_WIDTH</spirit:name>
        <spirit:displayName>C S00 Axi Data Width</spirit:displayName>
        <spirit:value spirit:format="long" spirit:resolve="generated" spirit:id="MODELPARAM_VALUE.C_S00_AXI_DATA_WIDTH">32</spirit:value>
      </spirit:modelParameter>
      <spirit:modelParameter spirit:dataType="integer">
        <spirit:name>C_S00_AXI_ADDR_WIDTH</spirit:name>
        <spirit:displayName>C S00 Axi Addr Width</spirit:displayName>
        <spirit:value spirit:format="long" spirit:resolve="generated" spirit:id="MODELPARAM_VALUE.C_S00_AXI_ADDR_WIDTH">7</spirit:value>
      </spirit:modelParameter>
    </spirit:modelParameters>
  </spirit:model>
  <spirit:choices>
    <spirit:choice>
      <spirit:name>choice_list_74b5137e</spirit:name>
      <spirit:enumeration>ACTIVE_HIGH</spirit:enumeration>
      <spirit:enumeration>ACTIVE_LOW</spirit:enumeration>
    </spirit:choice>
  </spirit:choices>
  <spirit:fileSets>
    <spirit:fileSet>
      <spirit:name>xilinx_xpgui_view_fileset</spirit:name>
      <spirit:file>
        <spirit:name>xgui/Version_v1_0.tcl</spirit:name>
        <spirit:fileType>tclSource</spirit:fileType>
        <spirit:userFileType>CHECKSUM_2367b3a1</spirit:userFileType>
        <spirit:userFileType>XGUI_VERSION_2</spirit:userFileType>
      </spirit:file>
    </spirit:fileSet>
  </spirit:fileSets>
  <spirit:description>xilinx.com:module_ref:Version:1.0</spirit:description>
  <spirit:parameters>
    <spirit:parameter>
      <spirit:name>VERSION_YYYY</spirit:name>
      <spirit:displayName>Version Yyyy</spirit:displayName>
      <spirit:value spirit:format="long" spirit:resolve="user" spirit:id="PARAM_VALUE.VERSION_YYYY">2025</spirit:value>
    </spirit:parameter>
    <spirit:parameter>
      <spirit:name>VERSION_MM</spirit:name>
      <spirit:displayName>Version Mm</spirit:displayName>
      <spirit:value spirit:format="long" spirit:resolve="user" spirit:id="PARAM_VALUE.VERSION_MM">8</spirit:value>
    </spirit:parameter>
    <spirit:parameter>
      <spirit:name>VERSION_DD</spirit:name>
      <spirit:displayName>Version Dd</spirit:displayName>
      <spirit:value spirit:format="long" spirit:resolve="user" spirit:id="PARAM_VALUE.VERSION_DD">14</spirit:value>
    </spirit:parameter>
    <spirit:parameter>
      <spirit:name>VERSION_MAJ</spirit:name>
      <spirit:displayName>Version Maj</spirit:displayName>
      <spirit:value spirit:format="long" spirit:resolve="user" spirit:id="PARAM_VALUE.VERSION_MAJ">0</spirit:value>
    </spirit:parameter>
    <spirit:parameter>
      <spirit:name>VERSION_MIN</spirit:name>
      <spirit:displayName>Version Min</spirit:displayName>
      <spirit:value spirit:format="long" spirit:resolve="user" spirit:id="PARAM_VALUE.VERSION_MIN">2</spirit:value>
    </spirit:parameter>
    <spirit:parameter>
      <spirit:name>VERSION_REV</spirit:name>
      <spirit:displayName>Version Rev</spirit:displayName>
      <spirit:value spirit:format="long" spirit:resolve="user" spirit:id="PARAM_VALUE.VERSION_REV">1</spirit:value>
    </spirit:parameter>
    <spirit:parameter>
      <spirit:name>VERSION_COMPANY</spirit:name>
      <spirit:displayName>Version Company</spirit:displayName>
      <spirit:value spirit:format="long" spirit:resolve="user" spirit:id="PARAM_VALUE.VERSION_COMPANY">1</spirit:value>
    </spirit:parameter>
    <spirit:parameter>
      <spirit:name>VERSION_MODE</spirit:name>
      <spirit:displayName>Version Mode</spirit:displayName>
      <spirit:value spirit:format="long" spirit:resolve="user" spirit:id="PARAM_VALUE.VERSION_MODE">1</spirit:value>
    </spirit:parameter>
    <spirit:parameter>
      <spirit:name>VERSION_BOARD</spirit:name>
      <spirit:displayName>Version Board</spirit:displayName>
      <spirit:value spirit:format="long" spirit:resolve="user" spirit:id="PARAM_VALUE.VERSION_BOARD">1</spirit:value>
    </spirit:parameter>
    <spirit:parameter>
      <spirit:name>VERSION_HW</spirit:name>
      <spirit:displayName>Version Hw</spirit:displayName>
      <spirit:value spirit:format="long" spirit:resolve="user" spirit:id="PARAM_VALUE.VERSION_HW">1</spirit:value>
    </spirit:parameter>
    <spirit:parameter>
      <spirit:name>NOTE_LENGTH</spirit:name>
      <spirit:displayName>Note Length</spirit:displayName>
      <spirit:value spirit:format="long" spirit:resolve="user" spirit:id="PARAM_VALUE.NOTE_LENGTH">112</spirit:value>
    </spirit:parameter>
    <spirit:parameter>
      <spirit:name>TEXT_0</spirit:name>
      <spirit:displayName>Text 0</spirit:displayName>
      <spirit:value spirit:resolve="user" spirit:id="PARAM_VALUE.TEXT_0">Viva</spirit:value>
    </spirit:parameter>
    <spirit:parameter>
      <spirit:name>TEXT_1</spirit:name>
      <spirit:displayName>Text 1</spirit:displayName>
      <spirit:value spirit:resolve="user" spirit:id="PARAM_VALUE.TEXT_1">do 2</spirit:value>
    </spirit:parameter>
    <spirit:parameter>
      <spirit:name>TEXT_2</spirit:name>
      <spirit:displayName>Text 2</spirit:displayName>
      <spirit:value spirit:resolve="user" spirit:id="PARAM_VALUE.TEXT_2">024.</spirit:value>
    </spirit:parameter>
    <spirit:parameter>
      <spirit:name>TEXT_3</spirit:name>
      <spirit:displayName>Text 3</spirit:displayName>
      <spirit:value spirit:resolve="user" spirit:id="PARAM_VALUE.TEXT_3">2 - </spirit:value>
    </spirit:parameter>
    <spirit:parameter>
      <spirit:name>TEXT_4</spirit:name>
      <spirit:displayName>Text 4</spirit:displayName>
      <spirit:value spirit:resolve="user" spirit:id="PARAM_VALUE.TEXT_4">    </spirit:value>
    </spirit:parameter>
    <spirit:parameter>
      <spirit:name>TEXT_5</spirit:name>
      <spirit:displayName>Text 5</spirit:displayName>
      <spirit:value spirit:resolve="user" spirit:id="PARAM_VALUE.TEXT_5">    </spirit:value>
    </spirit:parameter>
    <spirit:parameter>
      <spirit:name>TEXT_6</spirit:name>
      <spirit:displayName>Text 6</spirit:displayName>
      <spirit:value spirit:resolve="user" spirit:id="PARAM_VALUE.TEXT_6">    </spirit:value>
    </spirit:parameter>
    <spirit:parameter>
      <spirit:name>TEXT_7</spirit:name>
      <spirit:displayName>Text 7</spirit:displayName>
      <spirit:value spirit:resolve="user" spirit:id="PARAM_VALUE.TEXT_7">    </spirit:value>
    </spirit:parameter>
    <spirit:parameter>
      <spirit:name>TEXT_8</spirit:name>
      <spirit:displayName>Text 8</spirit:displayName>
      <spirit:value spirit:resolve="user" spirit:id="PARAM_VALUE.TEXT_8">    </spirit:value>
    </spirit:parameter>
    <spirit:parameter>
      <spirit:name>TEXT_9</spirit:name>
      <spirit:displayName>Text 9</spirit:displayName>
      <spirit:value spirit:resolve="user" spirit:id="PARAM_VALUE.TEXT_9">    </spirit:value>
    </spirit:parameter>
    <spirit:parameter>
      <spirit:name>TEXT_10</spirit:name>
      <spirit:displayName>Text 10</spirit:displayName>
      <spirit:value spirit:resolve="user" spirit:id="PARAM_VALUE.TEXT_10">    </spirit:value>
    </spirit:parameter>
    <spirit:parameter>
      <spirit:name>TEXT_11</spirit:name>
      <spirit:displayName>Text 11</spirit:displayName>
      <spirit:value spirit:resolve="user" spirit:id="PARAM_VALUE.TEXT_11">    </spirit:value>
    </spirit:parameter>
    <spirit:parameter>
      <spirit:name>TEXT_12</spirit:name>
      <spirit:displayName>Text 12</spirit:displayName>
      <spirit:value spirit:resolve="user" spirit:id="PARAM_VALUE.TEXT_12">    </spirit:value>
    </spirit:parameter>
    <spirit:parameter>
      <spirit:name>TEXT_13</spirit:name>
      <spirit:displayName>Text 13</spirit:displayName>
      <spirit:value spirit:resolve="user" spirit:id="PARAM_VALUE.TEXT_13">    </spirit:value>
    </spirit:parameter>
    <spirit:parameter>
      <spirit:name>TEXT_14</spirit:name>
      <spirit:displayName>Text 14</spirit:displayName>
      <spirit:value spirit:resolve="user" spirit:id="PARAM_VALUE.TEXT_14">    </spirit:value>
    </spirit:parameter>
    <spirit:parameter>
      <spirit:name>TEXT_15</spirit:name>
      <spirit:displayName>Text 15</spirit:displayName>
      <spirit:value spirit:resolve="user" spirit:id="PARAM_VALUE.TEXT_15">    </spirit:value>
    </spirit:parameter>
    <spirit:parameter>
      <spirit:name>TEXT_16</spirit:name>
      <spirit:displayName>Text 16</spirit:displayName>
      <spirit:value spirit:resolve="user" spirit:id="PARAM_VALUE.TEXT_16">    </spirit:value>
    </spirit:parameter>
    <spirit:parameter>
      <spirit:name>TEXT_17</spirit:name>
      <spirit:displayName>Text 17</spirit:displayName>
      <spirit:value spirit:resolve="user" spirit:id="PARAM_VALUE.TEXT_17">    </spirit:value>
    </spirit:parameter>
    <spirit:parameter>
      <spirit:name>TEXT_18</spirit:name>
      <spirit:displayName>Text 18</spirit:displayName>
      <spirit:value spirit:resolve="user" spirit:id="PARAM_VALUE.TEXT_18">    </spirit:value>
    </spirit:parameter>
    <spirit:parameter>
      <spirit:name>TEXT_19</spirit:name>
      <spirit:displayName>Text 19</spirit:displayName>
      <spirit:value spirit:resolve="user" spirit:id="PARAM_VALUE.TEXT_19">    </spirit:value>
    </spirit:parameter>
    <spirit:parameter>
      <spirit:name>TEXT_20</spirit:name>
      <spirit:displayName>Text 20</spirit:displayName>
      <spirit:value spirit:resolve="user" spirit:id="PARAM_VALUE.TEXT_20">    </spirit:value>
    </spirit:parameter>
    <spirit:parameter>
      <spirit:name>TEXT_21</spirit:name>
      <spirit:displayName>Text 21</spirit:displayName>
      <spirit:value spirit:resolve="user" spirit:id="PARAM_VALUE.TEXT_21">    </spirit:value>
    </spirit:parameter>
    <spirit:parameter>
      <spirit:name>TEXT_22</spirit:name>
      <spirit:displayName>Text 22</spirit:displayName>
      <spirit:value spirit:resolve="user" spirit:id="PARAM_VALUE.TEXT_22">    </spirit:value>
    </spirit:parameter>
    <spirit:parameter>
      <spirit:name>TEXT_23</spirit:name>
      <spirit:displayName>Text 23</spirit:displayName>
      <spirit:value spirit:resolve="user" spirit:id="PARAM_VALUE.TEXT_23">    </spirit:value>
    </spirit:parameter>
    <spirit:parameter>
      <spirit:name>TEXT_24</spirit:name>
      <spirit:displayName>Text 24</spirit:displayName>
      <spirit:value spirit:resolve="user" spirit:id="PARAM_VALUE.TEXT_24">    </spirit:value>
    </spirit:parameter>
    <spirit:parameter>
      <spirit:name>TEXT_25</spirit:name>
      <spirit:displayName>Text 25</spirit:displayName>
      <spirit:value spirit:resolve="user" spirit:id="PARAM_VALUE.TEXT_25">    </spirit:value>
    </spirit:parameter>
    <spirit:parameter>
      <spirit:name>TEXT_26</spirit:name>
      <spirit:displayName>Text 26</spirit:displayName>
      <spirit:value spirit:resolve="user" spirit:id="PARAM_VALUE.TEXT_26">    </spirit:value>
    </spirit:parameter>
    <spirit:parameter>
      <spirit:name>TEXT_27</spirit:name>
      <spirit:displayName>Text 27</spirit:displayName>
      <spirit:value spirit:resolve="user" spirit:id="PARAM_VALUE.TEXT_27">    </spirit:value>
    </spirit:parameter>
    <spirit:parameter>
      <spirit:name>C_S00_AXI_DATA_WIDTH</spirit:name>
      <spirit:displayName>C S00 Axi Data Width</spirit:displayName>
      <spirit:value spirit:format="long" spirit:resolve="user" spirit:id="PARAM_VALUE.C_S00_AXI_DATA_WIDTH">32</spirit:value>
    </spirit:parameter>
    <spirit:parameter>
      <spirit:name>C_S00_AXI_ADDR_WIDTH</spirit:name>
      <spirit:displayName>C S00 Axi Addr Width</spirit:displayName>
      <spirit:value spirit:format="long" spirit:resolve="user" spirit:id="PARAM_VALUE.C_S00_AXI_ADDR_WIDTH">7</spirit:value>
    </spirit:parameter>
    <spirit:parameter>
      <spirit:name>Component_Name</spirit:name>
      <spirit:value spirit:resolve="user" spirit:id="PARAM_VALUE.Component_Name" spirit:order="1">Version_v1_0</spirit:value>
    </spirit:parameter>
  </spirit:parameters>
  <spirit:vendorExtensions>
    <xilinx:coreExtensions>
      <xilinx:supportedFamilies>
        <xilinx:family xilinx:lifeCycle="Production">zynquplus</xilinx:family>
      </xilinx:supportedFamilies>
      <xilinx:taxonomies>
        <xilinx:taxonomy>/UserIP</xilinx:taxonomy>
      </xilinx:taxonomies>
      <xilinx:displayName>Version_v1_0</xilinx:displayName>
      <xilinx:autoFamilySupportLevel>level_1</xilinx:autoFamilySupportLevel>
      <xilinx:definitionSource>module_ref</xilinx:definitionSource>
      <xilinx:designToolContexts>
        <xilinx:designToolContext>IPI</xilinx:designToolContext>
      </xilinx:designToolContexts>
      <xilinx:coreRevision>1</xilinx:coreRevision>
      <xilinx:coreCreationDateTime>2025-09-10T05:23:50Z</xilinx:coreCreationDateTime>
    </xilinx:coreExtensions>
    <xilinx:packagingInfo>
      <xilinx:xilinxVersion>2024.2</xilinx:xilinxVersion>
    </xilinx:packagingInfo>
  </spirit:vendorExtensions>
</spirit:component>
